scicom/__init__.py
scicom/interface.py
scicom/run.py
scicom/simulations.md
scicom/data/NUTS_RG_60M_2021_3857_LEVL_2.geojson
scicom/data/nuts_rg_60M_2013_lvl_2.geojson
scicom/data/pone.0162678.s003.csv
scicom/data/relPop_plosOne.csv
scicom/historicalletters/__init__.py
scicom/historicalletters/agents.py
scicom/historicalletters/interface.py
scicom/historicalletters/model.py
scicom/historicalletters/space.py
scicom/historicalletters/utils.py
scicom/knowledgespread/SimpleContinuousModule.py
scicom/knowledgespread/__init__.py
scicom/knowledgespread/agents.py
scicom/knowledgespread/interface.py
scicom/knowledgespread/model.py
scicom/knowledgespread/server.py
scicom/knowledgespread/simple_continuous_canvas.js
scicom/knowledgespread/utils.py
scicom/utilities/__init__.py
scicom/utilities/statistics.py
scicom-1.0.1.dist-info/METADATA
scicom-1.0.1.dist-info/WHEEL
scicom-1.0.1.dist-info/licenses/AUTHORS.md
scicom-1.0.1.dist-info/licenses/LICENSE.md
scicom-1.0.1.dist-info/RECORD
