Metadata-Version: 2.4
Name: SciCom
Version: 1.0.1
Summary: Simulating various aspects of scientific communication via Agent-based models.
Project-URL: Project Homepage, https://modelsen.gea.mpg.de
Project-URL: Homepage, https://gitlab.gwdg.de/modelsen/sciencecommunicationmodels
Project-URL: Issues, https://gitlab.gwdg.de/modelsen/sciencecommunicationmodels/-/issues
Author-email: "Bernardo S. Buarque" <bernardo.buarque@motu.org.nz>, Malte Vogl <vogl@gea.mpg.de>
License: MIT License
License-File: AUTHORS.md
License-File: LICENSE.md
Classifier: License :: OSI Approved :: MIT License
Classifier: Operating System :: OS Independent
Classifier: Programming Language :: Python :: 3
Requires-Python: >3.8
Requires-Dist: altair
Requires-Dist: geopandas
Requires-Dist: igraph
Requires-Dist: mesa-geo
Requires-Dist: mesa>=2
Requires-Dist: networkx
Requires-Dist: numpy
Requires-Dist: nx-altair
Requires-Dist: pandas
Requires-Dist: shapely>=2
Requires-Dist: solara
Provides-Extra: dev
Requires-Dist: twine; extra == 'dev'
Provides-Extra: docs
Requires-Dist: myst-parser; extra == 'docs'
Requires-Dist: sphinx; extra == 'docs'
Requires-Dist: sphinx-autoapi; extra == 'docs'
Requires-Dist: sphinx-rtd-theme; extra == 'docs'
Provides-Extra: test
Requires-Dist: flake8; extra == 'test'
Requires-Dist: pytest; extra == 'test'
Requires-Dist: pytest-cov; extra == 'test'
Requires-Dist: tox; extra == 'test'
